habib_bitcoin_m/__init__.py
habib_bitcoin_m/__main__.py
habib_bitcoin_m/bitcoin_price_alert.py
habib_bitcoin_price-1.0.8.dist-info/LICENSE
habib_bitcoin_price-1.0.8.dist-info/METADATA
habib_bitcoin_price-1.0.8.dist-info/WHEEL
habib_bitcoin_price-1.0.8.dist-info/entry_points.txt
habib_bitcoin_price-1.0.8.dist-info/top_level.txt
habib_bitcoin_price-1.0.8.dist-info/RECORD
