Metadata-Version: 2.1
Name: habib-bitcoin-price
Version: 1.0.8
Summary: BITCOIN PRICE NOTIFICATION
Home-page: https://github.com/md-habibullah-au7/python_project
Author: Md Habibullah
Author-email: habibdeoraji@gmail.com
License: MIT
Platform: UNKNOWN
Classifier: License :: OSI Approved :: MIT License
Classifier: Programming Language :: Python :: 3
Classifier: Programming Language :: Python :: 3.7
Requires-Dist: requests
Requires-Dist: datetime
